matrixgen/__init__.py
matrixgen/cli.py
matrixgen/core.py
matrixgen/examples/dataset_generator.py
matrixgen/generators/bilinear.py
matrixgen/generators/dct.py
matrixgen/generators/fourier.py
matrixgen/generators/gaussian.py
matrixgen/generators/graph.py
matrixgen/generators/image.py
matrixgen/generators/lanczos.py
matrixgen/generators/nearest.py
matrixgen/generators/wavelet.py
matrixgen/py.typed
matrixgen/utils/features.py
matrixgen/utils/io.py
matrixgen/utils/visualize.py
matrixgen-0.1.0.dist-info/LICENSE
matrixgen-0.1.0.dist-info/METADATA
matrixgen-0.1.0.dist-info/WHEEL
matrixgen-0.1.0.dist-info/entry_points.txt
matrixgen-0.1.0.dist-info/RECORD
