Metadata-Version: 2.1
Name: matrixgen
Version: 0.1.0
Summary: Synthetic Sparse Matrix Generator
Home-page: https://github.com/He-Is-HaZaRdOuS/matrixgen
License: Apache-2.0
Author: Yousif Suhail
Author-email: yousifhazardous@gmail.com
Requires-Python: >=3.11,<4.0
Classifier: Development Status :: 3 - Alpha
Classifier: License :: OSI Approved :: Apache Software License
Classifier: Programming Language :: Python :: 3
Classifier: Programming Language :: Python :: 3.11
Classifier: Programming Language :: Python :: 3.12
Requires-Dist: click (>=8.0.1)
Requires-Dist: matplotlib (>=3.10.3,<4.0.0)
Requires-Dist: numpy (>=2.3.1,<3.0.0)
Requires-Dist: pywavelets (>=1.8.0,<2.0.0)
Requires-Dist: pyyaml (>=6.0.2,<7.0.0)
Requires-Dist: safety (>=3.5.2,<4.0.0)
Requires-Dist: scikit-image (>=0.25.2,<0.26.0)
Requires-Dist: scikit-learn (>=1.7.0,<2.0.0)
Requires-Dist: scipy (>=1.16.0,<2.0.0)
Project-URL: Changelog, https://github.com/He-Is-HaZaRdOuS/matrixgen/releases
Project-URL: Documentation, https://matrixgen.readthedocs.io
Project-URL: Repository, https://github.com/He-Is-HaZaRdOuS/matrixgen
